indra_curation/__init__.py
indra_curation/app.py
indra_curation/validation.py
tests/__init__.py
tests/test_validation.py
indra_curation-1.0.0.dist-info/LICENSE
indra_curation-1.0.0.dist-info/METADATA
indra_curation-1.0.0.dist-info/WHEEL
indra_curation-1.0.0.dist-info/top_level.txt
indra_curation-1.0.0.dist-info/RECORD
