Metadata-Version: 2.2
Name: indra_curation
Version: 1.0.0
Summary: INDRA Curation
Requires-Python: >=3.9
License-File: LICENSE
Requires-Dist: indra
Requires-Dist: flask
Requires-Dist: jinja2
Provides-Extra: s3
Requires-Dist: boto3; extra == "s3"
Provides-Extra: tests
Requires-Dist: pytest; extra == "tests"
